taxoniumtools/__init__.py
taxoniumtools/__main__.py
taxoniumtools/_version.py
taxoniumtools/newick_to_taxonium.py
taxoniumtools/parsimony_pb2.py
taxoniumtools/usher_to_taxonium.py
taxoniumtools/ushertools.py
taxoniumtools/utils.py
taxoniumtools/view_taxonium.py
taxoniumtools-2.1.23.dist-info/METADATA
taxoniumtools-2.1.23.dist-info/WHEEL
taxoniumtools-2.1.23.dist-info/entry_points.txt
taxoniumtools-2.1.23.dist-info/top_level.txt
taxoniumtools-2.1.23.dist-info/RECORD
