Metadata-Version: 2.4
Name: taxoniumtools
Version: 2.1.23
Summary: Generate files for taxonium
Home-page: https://github.com/theosanderson/taxonium
Author: Theo Sanderson
Author-email: theo@theo.io
Project-URL: Bug Tracker, https://github.com/theosanderson/taxonium/issues
Classifier: Programming Language :: Python :: 3
Classifier: License :: OSI Approved :: MIT License
Classifier: Operating System :: OS Independent
Requires-Python: >=3.8
Requires-Dist: treeswift
Requires-Dist: alive-progress
Requires-Dist: biopython<=1.81
Requires-Dist: pandas
Requires-Dist: google-api-python-client
Requires-Dist: protobuf<4
Requires-Dist: orjson
Requires-Dist: psutil
Requires-Dist: docker
